MANIFEST.in
README.md
setup.py
bin/ipasn-fullhistory_web
bin/ipasn_web
ipasn/__init__.py
ipasn/web/__init__.py
ipasn/web/api.py
ipasn_web.egg-info/PKG-INFO
ipasn_web.egg-info/SOURCES.txt
ipasn_web.egg-info/dependency_links.txt
ipasn_web.egg-info/requires.txt
ipasn_web.egg-info/top_level.txt