Metadata-Version: 1.1
Name: ipasn-web
Version: 1.0
Summary: Library to access the IP ASN History REST API.
Home-page: https://github.com/CIRCL/IP-ASN-history
Author: Raphaël Vinot
Author-email: raphael.vinot@circl.lu
License: UNKNOWN
Platform: UNKNOWN
Classifier: License :: OSI Approved :: GNU General Public License v3 (GPLv3)
Classifier: Development Status :: 5 - Production/Stable
Classifier: Environment :: Console
Classifier: Intended Audience :: Science/Research
Classifier: Intended Audience :: Telecommunications Industry
Classifier: Programming Language :: Python
Classifier: Topic :: Security
Classifier: Topic :: Internet
Classifier: Topic :: System :: Networking
